simple_http_fileserver/__init__.py
simple_http_fileserver/app.py
simple_http_fileserver/server.py
simple_http_fileserver-0.1.1.dist-info/METADATA
simple_http_fileserver-0.1.1.dist-info/WHEEL
simple_http_fileserver-0.1.1.dist-info/entry_points.txt
simple_http_fileserver-0.1.1.dist-info/top_level.txt
simple_http_fileserver-0.1.1.dist-info/RECORD
